rq_scheduler/__init__.py
rq_scheduler/scheduler.py
rq_scheduler/utils.py
rq_scheduler/scripts/__init__.py
rq_scheduler/scripts/rqscheduler.py
rq_scheduler_redux-0.12.0b3.dist-info/AUTHORS.rst
rq_scheduler_redux-0.12.0b3.dist-info/LICENSE.txt
rq_scheduler_redux-0.12.0b3.dist-info/METADATA
rq_scheduler_redux-0.12.0b3.dist-info/WHEEL
rq_scheduler_redux-0.12.0b3.dist-info/entry_points.txt
rq_scheduler_redux-0.12.0b3.dist-info/top_level.txt
rq_scheduler_redux-0.12.0b3.dist-info/RECORD
