Metadata-Version: 2.1
Name: rq-scheduler-redux
Version: 0.12.0b3
Summary: Provides job scheduling capabilities to RQ (Redis Queue)
Home-page: https://github.com/rq/rq-scheduler
Author: Selwin Ong
Author-email: selwin.ong@gmail.com
License: MIT
Classifier: Development Status :: 4 - Beta
Classifier: Environment :: Console
Classifier: Intended Audience :: Developers
Classifier: License :: OSI Approved :: MIT License
Classifier: Operating System :: OS Independent
Classifier: Programming Language :: Python :: 2
Classifier: Programming Language :: Python :: 2.7
Classifier: Programming Language :: Python :: 3
Classifier: Programming Language :: Python :: 3.5
Classifier: Programming Language :: Python :: 3.6
Classifier: Programming Language :: Python :: 3.7
Classifier: Programming Language :: Python :: 3.8
Classifier: Topic :: Software Development :: Libraries :: Python Modules
License-File: LICENSE.txt
License-File: AUTHORS.rst
Requires-Dist: crontab (>=0.23.0)
Requires-Dist: rq (>=0.13)
Requires-Dist: python-dateutil
Requires-Dist: freezegun
